schemagpt/__init__.py
schemagpt/exceptions.py
schemagpt/main.py
schemagpt/prompts.py
schemagpt/types.py
schemagpt-0.1.0.dist-info/LICENSE
schemagpt-0.1.0.dist-info/WHEEL
schemagpt-0.1.0.dist-info/METADATA
schemagpt-0.1.0.dist-info/RECORD
