Metadata-Version: 2.1
Name: schemagpt
Version: 0.1.0
Summary: Python library for RDF Schemas generation from prompts using GPT-3 magic 🪄🪄🪄
License: MIT
Author: Uladzislau Hubar
Author-email: hubar.uladzislau@gmail.com
Requires-Python: >=3.11,<4.0
Classifier: License :: OSI Approved :: MIT License
Classifier: Programming Language :: Python :: 3
Classifier: Programming Language :: Python :: 3.11
Requires-Dist: openai (>=0.26.4,<0.27.0)
